data/__init__.py
data/macaddress.io-db.json
data/settings.py
lib/__init__.py
lib/interfaces.py
lib/jsondata.py
lib/network.py
lib/process.py
lib/tools.py
little_owl-1.0.0.data/scripts/little_owl.py
obj/Adresse.py
obj/Machine.py
obj/Nic.py
obj/PcAdmin.py
obj/Reseau.py
obj/ReseauL2.py
obj/ReseauL3.py
obj/__init__.py
little_owl-1.0.0.dist-info/LICENCE
little_owl-1.0.0.dist-info/METADATA
little_owl-1.0.0.dist-info/WHEEL
little_owl-1.0.0.dist-info/entry_points.txt
little_owl-1.0.0.dist-info/top_level.txt
little_owl-1.0.0.dist-info/RECORD
