Metadata-Version: 2.1
Name: little-owl
Version: 1.0.0
Summary: Scanner de réseaux
Home-page: https://github.com/martialghy/little_owl
Author: Martial Goehry
Author-email: martial.goehry@gmail.com
License: UNKNOWN
Keywords: scan,sniff,network,discovery
Platform: UNKNOWN
Classifier: Development Status :: 5 - Production/Stable
Classifier: Environment :: Console
Classifier: Intended Audience :: System Administrators
Classifier: Natural Language :: French
Classifier: Operating System :: POSIX :: Linux
Classifier: License :: OSI Approved :: GNU General Public License v3 (GPLv3)
Classifier: Programming Language :: Python
Classifier: Programming Language :: Python :: 3
Classifier: Programming Language :: Python :: 3.4
Classifier: Programming Language :: Python :: 3.5
Classifier: Programming Language :: Python :: 3.6
Classifier: Topic :: System :: Networking
Requires-Dist: netifaces (>=0.10.4)
Requires-Dist: psutil (>=5.6.6)
Requires-Dist: scapy (>=2.4.3)
